{
  "id": "@Geralt1983/clickup-mcp-server-better",
  "displayName": "clickup-mcp-server-better",
  "description": "Manage ClickUp tasks, subtasks, tags, and documents with natural language. Create and visualize task dependencies, assign teammates, and organize work across spaces, folders, and lists. Track time, add comments and attachments, and speed up workflows with bulk actions.",
  "createdAt": "2026-01-17T02:12:22.838Z",
  "links": {
    "homepage": "",
    "registry": "https://smithery.ai/server/@Geralt1983/clickup-mcp-server-better"
  },
  "connection": {
    "type": "http",
    "runtime": "node",
    "configSchema": {
      "description": "Schema for the /mcp endpoint configuration"
    }
  },
  "capabilities": []
}