{
  "id": "@PewterZz/sf-dog-shelter-finder",
  "displayName": "San Francisco Dog Shelter Finder",
  "description": "Locate dog shelters within a specified radius in San Francisco using an easy-to-use API. Quickly find nearby shelters by providing a location and radius. Simplify your search for dog shelters with this dedicated tool.",
  "createdAt": "2026-01-17T02:20:58.089Z",
  "links": {
    "homepage": "",
    "registry": "https://smithery.ai/server/@PewterZz/sf-dog-shelter-finder"
  },
  "connection": {
    "type": "http",
    "runtime": "node",
    "configSchema": {
      "type": "object",
      "required": [],
      "properties": {
        "logLevel": {
          "type": "string",
          "description": "Log level for the server",
          "default": "info"
        }
      }
    }
  },
  "capabilities": []
}