{
  "id": "ai.smithery/zwldarren-akshare-one-mcp",
  "displayName": "ai.smithery/zwldarren-akshare-one-mcp",
  "description": "Provide access to Chinese stock market data including historical prices, real-time data, news, and…",
  "version": "1.14.0",
  "status": "active",
  "publishedAt": "2025-09-11T19:15:39.84882Z",
  "updatedAt": "2025-09-11T19:15:39.84882Z",
  "iconUrl": null,
  "websiteUrl": null,
  "repository": {
    "url": "https://github.com/zwldarren/akshare-one-mcp",
    "source": "github"
  },
  "packages": []
}